pyreact/__init__.py
pyreact/agent.py
pyreact/message.py
pyreact/clients/__init__.py
pyreact/clients/core.py
pyreact/clients/ollama.py
pyreact/docker_env/__init__.py
pyreact/docker_env/utils.py
pyreact/pipelines/__init__.py
pyreact/pipelines/ollama_react_pipeline.py
pyreact/tools/__init__.py
pyreact/tools/core.py
pyreact/tools/custom.py
pyreact/tools/docker_env.py
pyreact_agent/__init__.py
pyreact_agent/agent.py
pyreact_agent/message.py
pyreact_agent/clients/__init__.py
pyreact_agent/clients/core.py
pyreact_agent/clients/ollama.py
pyreact_agent/docker_env/__init__.py
pyreact_agent/docker_env/utils.py
pyreact_agent/pipelines/__init__.py
pyreact_agent/pipelines/dummy_pipeline.py
pyreact_agent/pipelines/ollama_react_pipeline.py
pyreact_agent/tools/__init__.py
pyreact_agent/tools/core.py
pyreact_agent/tools/custom.py
pyreact_agent/tools/docker_env.py
pyreact_agent-0.1.1.dist-info/LICENSE
pyreact_agent-0.1.1.dist-info/METADATA
pyreact_agent-0.1.1.dist-info/WHEEL
pyreact_agent-0.1.1.dist-info/top_level.txt
pyreact_agent-0.1.1.dist-info/RECORD
