Metadata-Version: 2.1
Name: pyreact-agent
Version: 0.1.1
Summary: A simple package to run a ReAct agent with Ollama and tools with privileges to run code inside a docker container.
Home-page: https://github.com/CodyAMaughan/pyreact-agent/
Author: Cody Maughan
Author-email: codyamaughan@gmail.com
Classifier: Programming Language :: Python :: 3
Classifier: License :: OSI Approved :: MIT License
Classifier: Operating System :: OS Independent
Requires-Python: >=3.9
License-File: LICENSE
Requires-Dist: requests
Requires-Dist: pydantic
Requires-Dist: docker
